LICENSE
MANIFEST.in
README.rst
setup.py
radpress/__init__.py
radpress/admin.py
radpress/compat.py
radpress/feeds.py
radpress/forms.py
radpress/mixins.py
radpress/models.py
radpress/settings.py
radpress/urls.py
radpress/views.py
radpress.egg-info/PKG-INFO
radpress.egg-info/SOURCES.txt
radpress.egg-info/dependency_links.txt
radpress.egg-info/not-zip-safe
radpress.egg-info/requires.txt
radpress.egg-info/top_level.txt
radpress/migrations/0001_initial.py
radpress/migrations/__init__.py
radpress/readers/__init__.py
radpress/readers/markdown_reader.py
radpress/readers/restructuredtext_reader.py
radpress/rst_extensions/__init__.py
radpress/rst_extensions/directive_pygments.py
radpress/rst_extensions/directive_radpress.py
radpress/rst_extensions/style_solarized.py
radpress/south_migrations/0001_initial.py
radpress/south_migrations/0002_auto__add_entryimage__add_field_article_cover_image.py
radpress/south_migrations/0003_auto__add_field_article_author.py
radpress/south_migrations/0004_radpress_article_authors.py
radpress/south_migrations/0005_auto__chg_field_page_updated_at__chg_field_article_updated_at.py
radpress/south_migrations/0006_zen_mode_integration.py
radpress/south_migrations/0007_add_markdown_to_renderers.py
radpress/south_migrations/__init__.py
radpress/static/radpress/css/main.css
radpress/static/radpress/css/zen_mode_admin.css
radpress/static/radpress/img/favicon.png
radpress/static/radpress/img/search.png
radpress/static/radpress/js/admin.js
radpress/static/radpress/js/jquery.js
radpress/static/radpress/js/script.js
radpress/static/radpress/js/taboverride.min.js
radpress/static/radpress/js/zen_mode.js
radpress/templates/admin/radpress/article/change_form.html
radpress/templates/radpress/article_archive.html
radpress/templates/radpress/article_detail.html
radpress/templates/radpress/article_list.html
radpress/templates/radpress/base.html
radpress/templates/radpress/base_no_body.html
radpress/templates/radpress/page_detail.html
radpress/templates/radpress/search.html
radpress/templates/radpress/zen_mode.html
radpress/templates/radpress/partials/archive_list.html
radpress/templates/radpress/partials/disqus.html
