Metadata-Version: 1.1
Name: radpress
Version: 0.4.3
Summary: Simple reusable blog application
Home-page: https://github.com/gkmngrgn/radpress
Author: Gökmen Görgen
Author-email: gokmen@radity.com
License: MIT
Platform: UNKNOWN
Classifier: Topic :: Software Development :: Libraries :: Python Modules
Classifier: Framework :: Django
Classifier: Environment :: Web Environment
Classifier: Programming Language :: Python
Classifier: Programming Language :: Python :: 2
Classifier: Programming Language :: Python :: 2.7
Classifier: Programming Language :: Python :: 3
Classifier: Programming Language :: Python :: 3.3
Classifier: Programming Language :: Python :: 3.4
